pyxy3d/__init__.py
pyxy3d/__main__.py
pyxy3d/calibration/capture_volume/capture_volume.py
pyxy3d/calibration/capture_volume/helper_functions/get_point_estimates.py
pyxy3d/calibration/capture_volume/helper_functions/get_stereotriangulated_table.py
pyxy3d/calibration/capture_volume/point_estimates.py
pyxy3d/calibration/capture_volume/quality_controller.py
pyxy3d/calibration/capture_volume/seaborn_summaries.py
pyxy3d/calibration/capture_volume/set_origin_functions.py
pyxy3d/calibration/charuco.py
pyxy3d/calibration/draw_charuco.py
pyxy3d/calibration/intrinsic_calibrator.py
pyxy3d/calibration/monocalibrator.py
pyxy3d/calibration/stereocalibrator.py
pyxy3d/cameras/camera.py
pyxy3d/cameras/camera_array.py
pyxy3d/cameras/camera_array_initializer.py
pyxy3d/cameras/live_stream.py
pyxy3d/cameras/synchronizer.py
pyxy3d/configurator.py
pyxy3d/controller.py
pyxy3d/export.py
pyxy3d/gui/calibrate_capture_volume_widget.py
pyxy3d/gui/camera_management/camera_display_widget.py
pyxy3d/gui/camera_management/multiplayback_widget.py
pyxy3d/gui/camera_management/playback_widget.py
pyxy3d/gui/charuco_widget.py
pyxy3d/gui/extrinsic_calibration_widget.py
pyxy3d/gui/extrinsic_playback_widget.py
pyxy3d/gui/frame_emitters/frame_dictionary_emitter.py
pyxy3d/gui/frame_emitters/playback_frame_emitter.py
pyxy3d/gui/frame_emitters/tools.py
pyxy3d/gui/icons/pyxy_logo.svg
pyxy3d/gui/icons/rotate-camera-left.svg
pyxy3d/gui/icons/rotate-camera-right.svg
pyxy3d/gui/log_widget.py
pyxy3d/gui/main_widget.py
pyxy3d/gui/old_main_widget.py
pyxy3d/gui/post_processing_widget.py
pyxy3d/gui/progress_dialog.py
pyxy3d/gui/recording_widget.py
pyxy3d/gui/synched_frames_display.py
pyxy3d/gui/vizualize/calibration/capture_volume_visualizer.py
pyxy3d/gui/vizualize/calibration/capture_volume_widget.py
pyxy3d/gui/vizualize/camera_mesh.py
pyxy3d/gui/vizualize/playback_triangulation_widget.py
pyxy3d/gui/vizualize/realtime_triangulation_widget.py
pyxy3d/gui/workspace_widget.py
pyxy3d/helper.py
pyxy3d/interface.py
pyxy3d-0.3.12.dist-info/entry_points.txt
pyxy3d-0.3.12.dist-info/LICENSE
pyxy3d-0.3.12.dist-info/METADATA
pyxy3d-0.3.12.dist-info/WHEEL
pyxy3d-0.3.12.dist-info/RECORD
