Metadata-Version: 2.1
Name: pyxy3d
Version: 0.3.12
Summary: GUI based multicamera calibration that integrates with 2D landmark tracking to triangulate 3D landmark positions
License: BSD-2-Clause
Author: Mac Prible
Author-email: prible@gmail.com
Requires-Python: >=3.10,<3.12
Classifier: License :: OSI Approved :: BSD License
Classifier: Programming Language :: Python :: 3
Classifier: Programming Language :: Python :: 3.10
Classifier: Programming Language :: Python :: 3.11
Requires-Dist: PyOpenGL (>=3.1.6,<4.0.0)
Requires-Dist: mediapipe (==0.10.1)
Requires-Dist: numba (>=0.57.0,<0.58.0)
Requires-Dist: opencv-contrib-python (>=4.8.0.74,<5.0.0.0)
Requires-Dist: pandas (>=1.5.0,<2.0.0)
Requires-Dist: pyqtdarktheme (>=2.1.0,<3.0.0)
Requires-Dist: pyqtgraph (>=0.13.2,<0.14.0)
Requires-Dist: pyside6 (>=6.5.2,<7.0.0)
Requires-Dist: rtoml (>=0.9.0,<0.10.0)
Requires-Dist: scipy (>=1.10.1,<2.0.0)
Project-URL: repository, https://github.com/mprib/pyxy3d
